{
  "$schema": "vscode://schemas/color-theme",
  "name": "FSociety Aura Black",
  "type": "dark",
  "semanticHighlighting": true,
  "colors": {
    "focusBorder": "#A277FF",
    "foreground": "#EDECEE",
    "descriptionForeground": "#ADACAE",
    "errorForeground": "#FF6767",
    "textBlockQuote.background": "#110F18",
    "textBlockQuote.border": "#4D466E",
    "textCodeBlock.background": "#15141B",
    "textLink.foreground": "#82E2FF",
    "textLink.activeForeground": "#44D7B6",
    "button.background": "#4D466E",
    "button.foreground": "#EDECEE",
    "button.hoverBackground": "#5A5380",
    "dropdown.background": "#15141B",
    "dropdown.foreground": "#EDECEE",
    "dropdown.border": "#3B334B",
    "input.background": "#15141B",
    "input.foreground": "#EDECEE",
    "input.border": "#4D466E",
    "input.placeholderForeground": "#6D6D6D",
    "inputOption.activeBorder": "#A277FF",
    "inputValidation.infoBorder": "#82E2FF",
    "inputValidation.warningBorder": "#7DA2FF",
    "inputValidation.errorBorder": "#FF6767",
    "badge.background": "#A277FF",
    "badge.foreground": "#15141B",
    "progressBar.background": "#A277FF",
    "titleBar.activeBackground": "#15141B",
    "titleBar.activeForeground": "#EDECEE",
    "titleBar.inactiveBackground": "#110F18",
    "titleBar.inactiveForeground": "#6D6D6D",
    "activityBar.background": "#15141B",
    "activityBar.foreground": "#44D7B6",
    "activityBar.inactiveForeground": "#525156",
    "activityBar.border": "#110F18",
    "activityBarBadge.background": "#A277FF",
    "activityBarBadge.foreground": "#15141B",
    "sideBar.background": "#15141B",
    "sideBar.foreground": "#EDECEE",
    "sideBar.border": "#110F18",
    "sideBarTitle.foreground": "#44D7B6",
    "sideBarSectionHeader.background": "#110F18",
    "sideBarSectionHeader.foreground": "#EDECEE",
    "sideBarSectionHeader.border": "#121016",
    "list.activeSelectionBackground": "#3B334B",
    "list.activeSelectionForeground": "#EDECEE",
    "list.inactiveSelectionBackground": "#2E2B38",
    "list.hoverBackground": "#24222C",
    "list.focusBackground": "#3B334B",
    "list.highlightForeground": "#44D7B6",
    "tree.indentGuidesStroke": "#3B334B",
    "editor.background": "#000000",
    "editor.foreground": "#EDECEE",
    "editorLineNumber.foreground": "#6D6D6D",
    "editorLineNumber.activeForeground": "#CDCCCE",
    "editorCursor.foreground": "#A277FF",
    "editor.selectionBackground": "#3D375E7F",
    "editor.selectionHighlightBackground": "#A394F033",
    "editor.wordHighlightBackground": "#3EA7847F",
    "editor.wordHighlightStrongBackground": "#3EA784AA",
    "editor.findMatchBackground": "#A277FF55",
    "editor.findMatchBorder": "#A277FF",
    "editor.findMatchHighlightBackground": "#A277FF2B",
    "editor.findMatchHighlightBorder": "#4D466E",
    "editor.findRangeHighlightBackground": "#3B334B66",
    "editor.hoverHighlightBackground": "#3B334B66",
    "editorIndentGuide.background1": "#24222C",
    "editorIndentGuide.activeBackground1": "#4D466E",
    "editorGutter.background": "#000000",
    "editorGutter.modifiedBackground": "#82E2FF",
    "editorGutter.addedBackground": "#44D7B6",
    "editorGutter.deletedBackground": "#FF6767",
    "editorWhitespace.foreground": "#24222C",
    "editorBracketMatch.background": "#3D375E66",
    "editorBracketMatch.border": "#A277FF",
    "editorWidget.background": "#15141B",
    "editorWidget.border": "#4D466E",
    "editorWidget.resizeBorder": "#A277FF",
    "editorSuggestWidget.background": "#15141B",
    "editorSuggestWidget.border": "#4D466E",
    "editorSuggestWidget.foreground": "#EDECEE",
    "editorSuggestWidget.highlightForeground": "#44D7B6",
    "editorSuggestWidget.selectedBackground": "#3B334B",
    "editorHoverWidget.background": "#15141B",
    "editorHoverWidget.border": "#4D466E",
    "editorOverviewRuler.findMatchForeground": "#A277FFAA",
    "editorOverviewRuler.selectionHighlightForeground": "#3EA784AA",
    "peekView.border": "#A277FF",
    "peekViewEditor.background": "#15141B",
    "peekViewEditor.matchHighlightBackground": "#A277FF38",
    "peekViewResult.background": "#110F18",
    "peekViewResult.selectionBackground": "#3B334B",
    "peekViewTitle.background": "#15141B",
    "diffEditor.insertedTextBackground": "#49C29A33",
    "diffEditor.removedTextBackground": "#FF474733",
    "merge.currentHeaderBackground": "#4D466EAA",
    "merge.incomingHeaderBackground": "#3EA7847F",
    "statusBar.background": "#15141B",
    "statusBar.foreground": "#EDECEE",
    "statusBar.border": "#110F18",
    "statusBar.debuggingBackground": "#A19C77",
    "statusBar.debuggingForeground": "#15141B",
    "statusBar.noFolderBackground": "#121016",
    "statusBarItem.hoverBackground": "#3B334B",
    "panel.background": "#15141B",
    "panel.border": "#110F18",
    "panelTitle.activeBorder": "#A277FF",
    "panelTitle.activeForeground": "#44D7B6",
    "panelTitle.inactiveForeground": "#6D6D6D",
    "tab.activeBackground": "#000000",
    "tab.activeForeground": "#44D7B6",
    "tab.inactiveBackground": "#15141B",
    "tab.inactiveForeground": "#6D6D6D",
    "tab.border": "#110F18",
    "tab.activeBorder": "#A277FF",
    "tab.unfocusedActiveBorder": "#4D466E",
    "editorGroupHeader.tabsBackground": "#15141B",
    "editorGroup.border": "#110F18",
    "scrollbarSlider.background": "#3D375E55",
    "scrollbarSlider.hoverBackground": "#4D466E77",
    "scrollbarSlider.activeBackground": "#A277FF88",
    "minimap.selectionHighlight": "#3D375E88",
    "minimap.findMatchHighlight": "#A277FF88",
    "minimap.errorHighlight": "#FF6767AA",
    "terminal.background": "#000000",
    "terminal.foreground": "#EDECEE",
    "terminalCursor.foreground": "#A277FF",
    "terminal.selectionBackground": "#3D375E7F",
    "terminal.ansiBlack": "#000000",
    "terminal.ansiRed": "#FF6767",
    "terminal.ansiGreen": "#44D7B6",
    "terminal.ansiYellow": "#7DA2FF",
    "terminal.ansiBlue": "#82E2FF",
    "terminal.ansiMagenta": "#A277FF",
    "terminal.ansiCyan": "#82E2FF",
    "terminal.ansiWhite": "#EDECEE",
    "terminal.ansiBrightBlack": "#6D6D6D",
    "terminal.ansiBrightRed": "#FF8A8A",
    "terminal.ansiBrightGreen": "#8DFFD9",
    "terminal.ansiBrightYellow": "#AFC1FF",
    "terminal.ansiBrightBlue": "#B4EEFF",
    "terminal.ansiBrightMagenta": "#C7A9FF",
    "terminal.ansiBrightCyan": "#B4EEFF",
    "terminal.ansiBrightWhite": "#FFFFFF"
  },
  "tokenColors": [
    {
      "name": "Comment",
      "scope": [
        "comment",
        "punctuation.definition.comment"
      ],
      "settings": {
        "foreground": "#6D6D6D",
        "fontStyle": "italic"
      }
    },
    {
      "name": "String",
      "scope": [
        "string",
        "punctuation.definition.string"
      ],
      "settings": {
        "foreground": "#44D7B6"
      }
    },
    {
      "name": "Keyword",
      "scope": [
        "keyword",
        "storage",
        "storage.type"
      ],
      "settings": {
        "foreground": "#A277FF"
      }
    },
    {
      "name": "Number and Constant",
      "scope": [
        "constant.numeric",
        "constant.language",
        "constant.character.escape"
      ],
      "settings": {
        "foreground": "#7DA2FF"
      }
    },
    {
      "name": "Function and Method",
      "scope": [
        "entity.name.function",
        "support.function",
        "meta.function-call",
        "variable.function"
      ],
      "settings": {
        "foreground": "#7DA2FF"
      }
    },
    {
      "name": "Type and Class",
      "scope": [
        "entity.name.type",
        "entity.name.class",
        "support.type",
        "support.class"
      ],
      "settings": {
        "foreground": "#82E2FF"
      }
    },
    {
      "name": "Variable",
      "scope": [
        "variable",
        "meta.definition.variable.name"
      ],
      "settings": {
        "foreground": "#A277FF"
      }
    },
    {
      "name": "Property",
      "scope": [
        "variable.other.property",
        "meta.object-literal.key"
      ],
      "settings": {
        "foreground": "#F694FF"
      }
    },
    {
      "name": "Invalid",
      "scope": [
        "invalid",
        "invalid.illegal"
      ],
      "settings": {
        "foreground": "#FF6767"
      }
    }
  ],
  "semanticTokenColors": {
    "namespace": "#A277FF",
    "class": "#82E2FF",
    "enum": "#82E2FF",
    "interface": "#82E2FF",
    "struct": "#82E2FF",
    "typeParameter": "#82E2FF",
    "type": "#82E2FF",
    "parameter": "#EDECEE",
    "variable": "#A277FF",
    "property": "#F694FF",
    "enumMember": "#7DA2FF",
    "decorator": "#F694FF",
    "function": "#7DA2FF",
    "method": "#7DA2FF",
    "keyword": "#A277FF",
    "comment": {
      "foreground": "#6D6D6D",
      "fontStyle": "italic"
    },
    "string": "#44D7B6",
    "number": "#7DA2FF"
  }
}
